eero/__init__.py
eero/client.py
eero/cookie_store.py
eero/eero.py
eero/exception.py
eero/session.py
eero/version.py
eero_km-0.0.6.dist-info/LICENSE
eero_km-0.0.6.dist-info/METADATA
eero_km-0.0.6.dist-info/WHEEL
eero_km-0.0.6.dist-info/top_level.txt
eero_km-0.0.6.dist-info/RECORD
