Metadata-Version: 2.1
Name: eero-km
Version: 0.0.6
Summary: Extract eero network details and insights
Home-page: https://github.com/krishnadasmallya/eero-client
Author: Krishnadas Mallya
Author-email: krishnadasmallya@gmail.com
License: MIT License
Keywords: eero-km
Platform: UNKNOWN
Classifier: Development Status :: 4 - Beta
Classifier: Intended Audience :: Developers
Classifier: Natural Language :: English
Classifier: Operating System :: OS Independent
Classifier: Programming Language :: Python
Classifier: Topic :: Software Development :: Libraries :: Python Modules
Classifier: Topic :: Utilities
Classifier: License :: OSI Approved :: MIT License
License-File: LICENSE
Requires-Dist: requests
Requires-Dist: click
Requires-Dist: pandas
Requires-Dist: PyYAML
